XiegeiRenleiDeJiqiXuexi/README.md
XiegeiRenleiDeJiqiXuexi/__init__.py
XiegeiRenleiDeJiqiXuexi/__main__.py
XiegeiRenleiDeJiqiXuexi/file.epub
XiegeiRenleiDeJiqiXuexi/index.html
XiegeiRenleiDeJiqiXuexi/css/__init__.py
XiegeiRenleiDeJiqiXuexi/css/annotations.css
XiegeiRenleiDeJiqiXuexi/css/main.css
XiegeiRenleiDeJiqiXuexi/css/normalize.css
XiegeiRenleiDeJiqiXuexi/css/popup.css
XiegeiRenleiDeJiqiXuexi/font/__init__.py
XiegeiRenleiDeJiqiXuexi/font/fontello.eot
XiegeiRenleiDeJiqiXuexi/font/fontello.svg
XiegeiRenleiDeJiqiXuexi/font/fontello.ttf
XiegeiRenleiDeJiqiXuexi/font/fontello.woff
XiegeiRenleiDeJiqiXuexi/img/__init__.py
XiegeiRenleiDeJiqiXuexi/img/annotator-glyph-sprite.png
XiegeiRenleiDeJiqiXuexi/img/annotator-icon-sprite.png
XiegeiRenleiDeJiqiXuexi/img/apple-touch-icon.png
XiegeiRenleiDeJiqiXuexi/img/cancelfullscreen.png
XiegeiRenleiDeJiqiXuexi/img/close.png
XiegeiRenleiDeJiqiXuexi/img/fullscreen.png
XiegeiRenleiDeJiqiXuexi/img/loader.gif
XiegeiRenleiDeJiqiXuexi/img/menu-icon.png
XiegeiRenleiDeJiqiXuexi/img/save.png
XiegeiRenleiDeJiqiXuexi/img/saved.png
XiegeiRenleiDeJiqiXuexi/img/settings-s.png
XiegeiRenleiDeJiqiXuexi/img/settings.png
XiegeiRenleiDeJiqiXuexi/img/star.png
XiegeiRenleiDeJiqiXuexi/js/__init__.py
XiegeiRenleiDeJiqiXuexi/js/epub.js
XiegeiRenleiDeJiqiXuexi/js/epub.min.js
XiegeiRenleiDeJiqiXuexi/js/epub.min.map
XiegeiRenleiDeJiqiXuexi/js/hooks.min.js
XiegeiRenleiDeJiqiXuexi/js/hooks.min.map
XiegeiRenleiDeJiqiXuexi/js/reader.js
XiegeiRenleiDeJiqiXuexi/js/reader.js.map
XiegeiRenleiDeJiqiXuexi/js/reader.min.js
XiegeiRenleiDeJiqiXuexi/js/reader.min.map
XiegeiRenleiDeJiqiXuexi/js/hooks/__init__.py
XiegeiRenleiDeJiqiXuexi/js/hooks/extensions/__init__.py
XiegeiRenleiDeJiqiXuexi/js/hooks/extensions/highlight.js
XiegeiRenleiDeJiqiXuexi/js/libs/__init__.py
XiegeiRenleiDeJiqiXuexi/js/libs/jquery.min.js
XiegeiRenleiDeJiqiXuexi/js/libs/localforage.min.js
XiegeiRenleiDeJiqiXuexi/js/libs/screenfull.js
XiegeiRenleiDeJiqiXuexi/js/libs/screenfull.min.js
xiegei_renlei_de_jiqi_xuexi-2024.3.2.0.dist-info/METADATA
xiegei_renlei_de_jiqi_xuexi-2024.3.2.0.dist-info/WHEEL
xiegei_renlei_de_jiqi_xuexi-2024.3.2.0.dist-info/entry_points.txt
xiegei_renlei_de_jiqi_xuexi-2024.3.2.0.dist-info/top_level.txt
xiegei_renlei_de_jiqi_xuexi-2024.3.2.0.dist-info/RECORD
